{
  "id_articulo": "Art. 278",
  "titulo": "Art. 278. Costo mínimo de los inmuebles adquiridos con prestamos.",
  "titulo_corto": "Costo mínimo de los inmuebles adquiridos con prestamos.",
  "slug": "278",
  "url_origen": "https://estatuto.co/278",
  "libro": "Libro I - Renta",
  "libro_full": "I - Impuesto sobre la Renta y Complementarios",
  "estado": "vigente",
  "complexity_score": 0,
  "contenido_texto": "Cuando se adquieran bienes raíces con préstamos de entidades sometidas a la vigilancia el Estado, el precio de compra fijado en la escritura no podrá ser inferior a na suma en la cual el préstamo represente el 70% del total. Los notarios se abstendrán de autorizar las escrituras que no cumplan con este requisito.",
  "contenido_html": "<span class=\"ct-span oxy-stock-content-styles\" id=\"span-8-7\"><p>Cuando se adquieran bienes raíces con préstamos de entidades sometidas a la vigilancia el Estado, el precio de compra fijado en la escritura no podrá ser inferior a na suma en la cual el préstamo represente el 70% del total.</p>\n<p>Los notarios se abstendrán de autorizar las escrituras que no cumplan con este requisito.</p>\n</span>",
  "modificaciones_raw": "",
  "modificaciones_parsed": [],
  "total_modificaciones": 0,
  "ultima_modificacion_year": null,
  "leyes_modificatorias": [],
  "texto_derogado": [],
  "texto_derogado_parsed": [],
  "normas_parsed": {
    "jurisprudencia": [],
    "decretos": [],
    "doctrina_dian": [],
    "notas": [],
    "otros": []
  },
  "total_normas": 0,
  "cross_references": [],
  "referenced_by": [],
  "total_cross_references": 0,
  "concordancias": "Jurisprudencia: 8 sentencia(s) relacionada(s)",
  "doctrina_dian_scrape": "oficio 26835 (2019-10-24): Financiaci&oacute;n del valor de venta en el sector vivienda\noficio 27784 (2017-10-11): Patrimonio - usufructo - Nuda propiedad Renta presuntiva\noficio 9674 (2015-03-31): Aportes a sociedades nacionales - Elusi&oacute;n fiscal Facultad fiscalizadora - Fraude fiscal - R&eacute;gimen tributario en los casos de supresi&oacute;n, fusi&oacute;n, transformaci&oacute;n de entidades u organismos p&uacute;blicos del orden nacional\noficio 66597 (2010-09-10): &iquest;Trat&aacute;ndose de cr&eacute;ditos de vivienda a largo plazo otorgados por entidades sometidas a la vigilancia del Estado, los notarios pueden autorizar escrituras p&uacute;blicas, cuando el valor del pr&eacute;stamo, supere el setenta por ciento (70%) del precio de compra?\nconcepto 0087705 (2007-10-26): &iquest;En la transferencia de bienes en virtud del contrato de leasing inmobiliario se debe observar que el valor del bien no sea inferior a una suma en la cual el valor del cr&eacute;dito represente el setenta por ciento (70%) del valor total, para que el notario autorice la escritura p&uacute;blica?",
  "notas_editoriales": "",
  "jurisprudencia_vinculada": [
    {
      "id": "cc-c-016-2004",
      "corte": "constitucional",
      "tipo": "C",
      "numero": "016",
      "year": 2004
    },
    {
      "id": "cc-c-760-2001",
      "corte": "constitucional",
      "tipo": "C",
      "numero": "760",
      "year": 2001,
      "decision": "exequible"
    },
    {
      "id": "cc-c-1039-2004",
      "corte": "constitucional",
      "tipo": "C",
      "numero": "1039",
      "year": 2004
    },
    {
      "id": "cc-c-646-2001",
      "corte": "constitucional",
      "tipo": "C",
      "numero": "646",
      "year": 2001,
      "decision": "exequible"
    },
    {
      "id": "cc-c-112-2019",
      "corte": "constitucional",
      "tipo": "C",
      "numero": "112",
      "year": 2019,
      "decision": "exequible condicionada"
    },
    {
      "id": "cc-c-633-2016",
      "corte": "constitucional",
      "tipo": "C",
      "numero": "633",
      "year": 2016,
      "decision": "exequible"
    },
    {
      "id": "cc-c-365-2012",
      "corte": "constitucional",
      "tipo": "C",
      "numero": "365",
      "year": 2012
    },
    {
      "id": "cc-c-988-2006",
      "corte": "constitucional",
      "tipo": "C",
      "numero": "988",
      "year": 2006,
      "decision": "exequible"
    }
  ],
  "doctrina_vinculada": [
    {
      "id": "dian-oficio-26835-2019",
      "tipo": "oficio",
      "numero": "26835",
      "fecha": "2019-10-24",
      "tema": "Financiaci&oacute;n del valor de venta en el sector vivienda",
      "vigente": true
    },
    {
      "id": "dian-oficio-27784-2017",
      "tipo": "oficio",
      "numero": "27784",
      "fecha": "2017-10-11",
      "tema": "Patrimonio - usufructo - Nuda propiedad Renta presuntiva",
      "vigente": true
    },
    {
      "id": "dian-oficio-9674-2015",
      "tipo": "oficio",
      "numero": "9674",
      "fecha": "2015-03-31",
      "tema": "Aportes a sociedades nacionales - Elusi&oacute;n fiscal Facultad fiscalizadora - Fraude fiscal - R&eacute;gimen tributario en los casos de supresi&oacute;n, fusi&oacute;n, transformaci&oacute;n de entidades u organismos p&uacute;blicos del orden nacional",
      "vigente": true
    },
    {
      "id": "dian-oficio-66597-2010",
      "tipo": "oficio",
      "numero": "66597",
      "fecha": "2010-09-10",
      "tema": "&iquest;Trat&aacute;ndose de cr&eacute;ditos de vivienda a largo plazo otorgados por entidades sometidas a la vigilancia del Estado, los notarios pueden autorizar escrituras p&uacute;blicas, cuando el valor del pr&eacute;stamo, supere el setenta por ciento (70%) del precio de compra?",
      "vigente": true
    },
    {
      "id": "dian-concepto-0087705-2007",
      "tipo": "concepto",
      "numero": "0087705",
      "fecha": "2007-10-26",
      "tema": "&iquest;En la transferencia de bienes en virtud del contrato de leasing inmobiliario se debe observar que el valor del bien no sea inferior a una suma en la cual el valor del cr&eacute;dito represente el setenta por ciento (70%) del valor total, para que el notario autorice la escritura p&uacute;blica?",
      "vigente": true
    },
    {
      "id": "dian-concepto-0085084-2004",
      "tipo": "concepto",
      "numero": "0085084",
      "fecha": "2004-12-02",
      "tema": "&iquest;Cu&aacute;les son las entidades sometidas a la vigilancia del estado a las que refiere el art&iacute;culo 278 del estatuto tributario, para efectos de establecer el costo m&iacute;nimo de los bienes inmuebles que se adquieren con pr&eacute;stamos?",
      "vigente": true
    }
  ]
}