{"id_articulo": "Art. 462", "titulo": "Art. 462. Base gravable para el servicio telefónico.", "titulo_corto": "Base gravable para el servicio telefónico.", "slug": "462", "url_origen": "https://estatuto.co/462", "libro": "Libro III - IVA", "libro_full": "III - Impuesto sobre las Ventas", "estado": "vigente", "complexity_score": 1, "contenido_texto": "*La base gravable en el servicio telefónico es la general, contemplada en el artículo 447 del Estatuto Tributario.", "contenido_html": "<span class=\"ct-span oxy-stock-content-styles\" id=\"span-8-7\"><p>*La base gravable en el servicio telefónico es la general, contemplada en el<a href=\"https://estatuto.co/447\" rel=\"noopener\" target=\"_blank\"> artículo 447</a> del Estatuto Tributario.</p>\n</span>", "modificaciones_raw": "*Subrogado Ley 488 de 1998 Art 55.", "modificaciones_parsed": [], "total_modificaciones": 0, "ultima_modificacion_year": null, "leyes_modificatorias": [], "texto_derogado": [], "texto_derogado_parsed": [], "normas_parsed": {"jurisprudencia": [], "decretos": [], "doctrina_dian": [], "notas": [], "otros": []}, "total_normas": 0, "cross_references": ["447"], "referenced_by": [], "total_cross_references": 1, "concordancias": "", "doctrina_dian_scrape": "", "notas_editoriales": ""}