{"id_articulo": "Art. 650", "titulo": "Art. 650. Sanción por uso fraudulento de cedulas.", "titulo_corto": "Sanción por uso fraudulento de cedulas.", "slug": "650", "url_origen": "https://estatuto.co/650", "libro": "Libro V - Procedimiento", "libro_full": "V - Procedimiento Tributario", "estado": "vigente", "complexity_score": 1, "contenido_texto": "El contribuyente o responsable que utilice fraudulentamente en sus informaciones tributarias cédulas de personas fallecidas o inexistentes, será denunciado como autor de fraude procesal. La Administración Tributaria desconocerá los costos, deducciones, descuentos y pasivos patrimoniales cuando la identificación de los beneficiarios no corresponda a cédulas vigentes, y tal error no podrá ser subsanado posteriormente, a menos que el contribuyente o responsable pruebe que la operación se realizó antes del fallecimiento de la persona cuya cédula fue informada, o con su sucesión.", "contenido_html": "<span class=\"ct-span oxy-stock-content-styles\" id=\"span-8-7\"><p>El contribuyente o responsable que utilice fraudulentamente en sus informaciones tributarias cédulas de personas fallecidas o inexistentes, será denunciado como autor de fraude procesal.</p>\n<p>La Administración Tributaria desconocerá los costos, deducciones, descuentos y pasivos patrimoniales cuando la identificación de los beneficiarios no corresponda a cédulas vigentes, y tal error no podrá ser subsanado posteriormente, a menos que el contribuyente o responsable pruebe que la operación se realizó antes del fallecimiento de la persona cuya cédula fue informada, o con su sucesión.</p>\n</span>", "modificaciones_raw": "", "modificaciones_parsed": [], "total_modificaciones": 0, "ultima_modificacion_year": null, "leyes_modificatorias": [], "texto_derogado": [], "texto_derogado_parsed": [], "normas_parsed": {"jurisprudencia": [], "decretos": [], "doctrina_dian": [], "notas": [], "otros": []}, "total_normas": 0, "cross_references": [], "referenced_by": [], "total_cross_references": 0, "concordancias": "", "doctrina_dian_scrape": "", "notas_editoriales": ""}