{"id_articulo": "Art. 786", "titulo": "Art. 786. Las de los ingresos no constitutivos de renta.", "titulo_corto": "Las de los ingresos no constitutivos de renta.", "slug": "786", "url_origen": "https://estatuto.co/786", "libro": "Libro V - Procedimiento", "libro_full": "V - Procedimiento Tributario", "estado": "vigente", "complexity_score": 0, "contenido_texto": "Cuando exista alguna prueba distinta de la declaración de renta y complementarios del contribuyente, sobre la existencia de un ingreso, y éste alega haberlo recibido en circunstancias que no lo hacen constitutivo de renta, está obligado a demostrar tales circunstancias.", "contenido_html": "<span class=\"ct-span oxy-stock-content-styles\" id=\"span-8-7\"><p>Cuando exista alguna prueba distinta de la declaración de renta y complementarios del contribuyente, sobre la existencia de un ingreso, y éste alega haberlo recibido en circunstancias que no lo hacen constitutivo de renta, está obligado a demostrar tales circunstancias.</p>\n</span>", "modificaciones_raw": "", "modificaciones_parsed": [], "total_modificaciones": 0, "ultima_modificacion_year": null, "leyes_modificatorias": [], "texto_derogado": [], "texto_derogado_parsed": [], "normas_parsed": {"jurisprudencia": [], "decretos": [], "doctrina_dian": [], "notas": [], "otros": []}, "total_normas": 0, "cross_references": [], "referenced_by": [], "total_cross_references": 0, "concordancias": "", "doctrina_dian_scrape": "", "notas_editoriales": ""}